{
    "25": {
        "code": "2567",
        "event_order": [1,3,2,1,2],
        "event_time": [0,1,3,5,6],
        "pipe_lineup":[
        2, 3, 2,
        3, 2, 4,
        1, 3, 2
        ],
        "pipe_code":[
        "5823", "1642", "1989",
        "1150", "2117", "0507",
        "1321", "9768", "1617"
        ],
        "pipe_rotate":[
        180, 90, 0,
        0, 0, 0,
        0, 0, 0
        ],
        "vr_electic":["16579", "51276", "14682"],
        "web_electic":["04832", "84930", "30751"],
        "dirt":0,
        "passcode": [
        "5167",
        "6147",
        "4908",
        "4967",
        "3909"
        ]
    },
    "14":{
        "code": "1412",
        "event_order": [1,2,3,2,1],
        "event_time": [0,2,3,5,5],
        "pipe_lineup":[
        2, 3, 2,
        3, 2, 4,
        1, 3, 2
        ],
        "pipe_code":[
        "5823", "1642", "1989",
        "1150", "2117", "0507",
        "1321", "9768", "1617"
        ],
        "pipe_rotate":[
        180, 90, 0,
        0, 0, 0,
        0, 0, 0
        ],
        "vr_electic":["16579", "51276", "14682"],
        "web_electic":["04832", "84930", "30751"],
        "dirt":0,
        "passcode": [
        "5167",
        "6147",
        "4908",
        "4967",
        "3909"
        ]
    }
}